cm/__init__.py
cm/scraper.py
cm_scraper-0.1.2.dist-info/METADATA
cm_scraper-0.1.2.dist-info/WHEEL
cm_scraper-0.1.2.dist-info/entry_points.txt
cm_scraper-0.1.2.dist-info/top_level.txt
cm_scraper-0.1.2.dist-info/RECORD
