Metadata-Version: 2.1
Name: cm-scraper
Version: 0.1.2
Summary: A scraper for Channel Myanmar movies
Home-page: https://github.com/konyilwin/cm-scraper
Author: Nyi Nyi Lwin
Author-email: hello@nyinyilwin.com
Classifier: Programming Language :: Python :: 3
Classifier: License :: OSI Approved :: MIT License
Classifier: Operating System :: OS Independent
Requires-Python: >=3.6
Requires-Dist: requests ==2.26.0
Requires-Dist: beautifulsoup4 ==4.9.3
